json_to_models/__init__.py
json_to_models-0.0.4.dist-info/METADATA
json_to_models-0.0.4.dist-info/WHEEL
json_to_models-0.0.4.dist-info/top_level.txt
json_to_models-0.0.4.dist-info/RECORD
